jax_scalify/__init__.py
jax_scalify/version.py
jax_scalify/core/__init__.py
jax_scalify/core/datatype.py
jax_scalify/core/debug.py
jax_scalify/core/interpreters.py
jax_scalify/core/pow2.py
jax_scalify/core/typing.py
jax_scalify/core/utils.py
jax_scalify/lax/__init__.py
jax_scalify/lax/base_scaling_primitives.py
jax_scalify/lax/scaled_ops_common.py
jax_scalify/lax/scaled_ops_l2.py
jax_scalify/ops/__init__.py
jax_scalify/ops/cast.py
jax_scalify/ops/debug.py
jax_scalify/ops/rescaling.py
jax_scalify/ops/utils.py
jax_scalify/tree/__init__.py
jax_scalify/tree/tree_util.py
jax_scalify-0.1.1.dist-info/LICENSE
jax_scalify-0.1.1.dist-info/METADATA
jax_scalify-0.1.1.dist-info/WHEEL
jax_scalify-0.1.1.dist-info/top_level.txt
jax_scalify-0.1.1.dist-info/RECORD
