Metadata-Version: 2.1
Name: jax_scalify
Version: 0.1.1
Summary: JAX Scalify: end-to-end scaled arithmetic.
Author-email: Paul Balanca <paulb@graphcore.ai>
Project-URL: Homepage, https://github.com/graphcore-research/jax-scalify/#readme
Project-URL: Bug Reports, https://github.com/graphcore-research/jax-scalify/issues
Project-URL: Source, https://github.com/graphcore-research/jax-scalify/
Classifier: Development Status :: 3 - Alpha
Classifier: Intended Audience :: Developers
Classifier: Intended Audience :: Science/Research
Classifier: License :: OSI Approved :: Apache Software License
Classifier: Programming Language :: Python :: 3.10
Classifier: Programming Language :: Python :: 3.11
Classifier: Topic :: Scientific/Engineering :: Artificial Intelligence
Requires-Python: >=3.10
License-File: LICENSE
Requires-Dist: chex >=0.1.6
Requires-Dist: jax >=0.3.16
Requires-Dist: jaxlib >=0.3.15
Requires-Dist: ml-dtypes
Requires-Dist: numpy >=1.22.4
Provides-Extra: dev
Requires-Dist: check-manifest ; extra == 'dev'
Provides-Extra: test
Requires-Dist: pytest ; extra == 'test'
